LR1STPKG/__init__.py
LR1STPKG/model_a.py
LR1STPKG/model_b.py
LR1STPKG-0.1.dist-info/METADATA
LR1STPKG-0.1.dist-info/WHEEL
LR1STPKG-0.1.dist-info/top_level.txt
LR1STPKG-0.1.dist-info/RECORD
