Metadata-Version: 2.1
Name: LR1STPKG
Version: 0.1
Summary: A simple Python package named LR1STPKG
Author: Your Name
Author-email: your@email.com
